pyFaulT2RePol/FaultTree.py
pyFaulT2RePol/FaultTreeR.py
pyFaulT2RePol/HasseDiagramLib.py
pyFaulT2RePol/LogicGate.py
pyFaulT2RePol/__init__.py
pyFaulT2RePol-0.1.dist-info/LICENSE.txt
pyFaulT2RePol-0.1.dist-info/METADATA
pyFaulT2RePol-0.1.dist-info/WHEEL
pyFaulT2RePol-0.1.dist-info/top_level.txt
pyFaulT2RePol-0.1.dist-info/RECORD
