Metadata-Version: 2.1
Name: pyFaulT2RePol
Version: 0.1
Summary: Reliability by Sastifiability
Home-page: UNKNOWN
Author: David Jaures Fotsa-Mbogne, Guy-de-patience Ftatsi-Mbetmi
Author-email: jauresfotsa@gmail.com, fimigype@gmail.com
License: UNKNOWN
Platform: UNKNOWN
Classifier: Programming Language :: Python :: 3
Classifier: License :: OSI Approved :: MIT License
Classifier: Operating System :: OS Independent
